integration_pip_inspector
