Metadata-Version: 1.0
Name: integration-pip-inspector
Version: 0.0.3
Summary: Generates and deploys Black Duck I/O files for use with the Black Duck Hub
Home-page: https://github.com/blackducksoftware/hub-pip
Author: Black Duck Software
Author-email: bdsoss@blackducksoftware.com
License: Apache 2.0
Keywords: integration_pip_inspector blackduck hub
Platform: UNKNOWN
